htmlviewer/__init__.py
htmlviewer/core.py
htmlviewer/pagination.py
htmlviewer/templates/colResizable-1.6.min.js
htmlviewer/templates/viewer.css
htmlviewer/templates/viewer.html
htmlviewer/templates/viewer.js
htmlviewer/util.py
htmlviewer-0.1.7.dist-info/LICENSE
htmlviewer-0.1.7.dist-info/WHEEL
htmlviewer-0.1.7.dist-info/METADATA
htmlviewer-0.1.7.dist-info/RECORD
