Metadata-Version: 2.1
Name: htmlviewer
Version: 0.1.7
Summary: Table viewer for relational databases, without using HandsOnTable.
Home-page: https://github.com/patarapolw/htmlviewer
License: MIT
Author: Pacharapol Withayasakpunt
Author-email: patarapolw@gmail.com
Classifier: License :: OSI Approved :: MIT License
Classifier: Programming Language :: Python :: 2
Classifier: Programming Language :: Python :: 2.7
Classifier: Programming Language :: Python :: 3
Classifier: Programming Language :: Python :: 3.4
Classifier: Programming Language :: Python :: 3.5
Classifier: Programming Language :: Python :: 3.6
Classifier: Programming Language :: Python :: 3.7
Requires-Dist: jinja2 (>=2.10,<3.0)
Requires-Dist: jupyter (>=1.0,<2.0)
Requires-Dist: notebook (>=5.7,<6.0)
